pynboard/__init__.py
pynboard/actions.py
pynboard/core.py
pynboard/display_properties.py
pynboard/html_buffer.py
pynboard/utils.py
pynboard-0.0.7.dist-info/METADATA
pynboard-0.0.7.dist-info/WHEEL
pynboard-0.0.7.dist-info/licenses/LICENSE
pynboard-0.0.7.dist-info/RECORD
